LICENSE
README.md
setup.cfg
setup.py
sharedshell/__init__.py
sharedshell/sharedshell.py
sharedshell.egg-info/PKG-INFO
sharedshell.egg-info/SOURCES.txt
sharedshell.egg-info/dependency_links.txt
sharedshell.egg-info/top_level.txt