Metadata-Version: 2.1
Name: sharedshell
Version: 0.0.3
Summary: This package adds the posibility of running commands in a shared shell
Home-page: https://www.github.com/sersanchus/sharedshell
Author: Sergio Sancho Chust
Author-email: sersanchus@gmail.com
License: UNKNOWN
Platform: UNKNOWN
Classifier: Programming Language :: Python :: 3
Classifier: License :: OSI Approved :: MIT License
Classifier: Operating System :: OS Independent
License-File: LICENSE
